{
  "artifacts": [
    {
      "file": "com/android/tools/build/gradle-api/8.0.0-beta04/gradle-api-8.0.0-beta04.pom",
      "repo": "https://maven.google.com/",
      "artifact": "com.android.tools.build:gradle-api:pom:8.0.0-beta04"
    },
    {
      "file": "com/android/tools/build/gradle-api/8.0.0-beta04/gradle-api-8.0.0-beta04.jar",
      "repo": "https://maven.google.com/",
      "artifact": "com.android.tools.build:gradle-api:jar:8.0.0-beta04"
    },
    {
      "file": "com/android/tools/build/gradle-api/8.0.0-beta04/gradle-api-8.0.0-beta04.module",
      "repo": "https://maven.google.com/",
      "artifact": "com.android.tools.build:gradle-api:module:8.0.0-beta04"
    }
  ]
}