{
  "artifacts": [
    {
      "file": "com/android/tools/build/gradle-api/8.2.0-alpha10/gradle-api-8.2.0-alpha10.pom",
      "repo": "https://maven.google.com/",
      "artifact": "com.android.tools.build:gradle-api:pom:8.2.0-alpha10"
    },
    {
      "file": "com/android/tools/build/gradle-api/8.2.0-alpha10/gradle-api-8.2.0-alpha10.jar",
      "repo": "https://maven.google.com/",
      "artifact": "com.android.tools.build:gradle-api:jar:8.2.0-alpha10"
    },
    {
      "file": "com/android/tools/build/gradle-api/8.2.0-alpha10/gradle-api-8.2.0-alpha10.module",
      "repo": "https://maven.google.com/",
      "artifact": "com.android.tools.build:gradle-api:module:8.2.0-alpha10"
    }
  ]
}