{
  "artifacts": [
    {
      "file": "org/abego/treelayout/org.abego.treelayout.core/1.0.1/org.abego.treelayout.core-1.0.1.pom",
      "repo": "https://plugins.gradle.org/m2",
      "artifact": "org.abego.treelayout:org.abego.treelayout.core:pom:1.0.1"
    },
    {
      "file": "org/abego/treelayout/org.abego.treelayout.core/1.0.1/org.abego.treelayout.core-1.0.1.jar",
      "repo": "https://plugins.gradle.org/m2",
      "artifact": "org.abego.treelayout:org.abego.treelayout.core:jar:1.0.1"
    }
  ]
}